Question6/Johnson_counter.v
module D_FlipFlop(input D,clk,rst,output reg Q );
    always @(posedge clk or negedge rst) begin
        if(!rst)
            Q<=0;
        else
            Q<=D;
    end
endmodule
module Johnson_counter #(parameter N=4)(input rst,clk,output [N-1:0]Q);
    genvar ii;
    generate
        for (ii=0;ii<N;ii=ii+1) begin
            if(ii==0) begin
                D_FlipFlop d(~Q[N-1],clk,rst,Q[ii]);
            end
            else begin
                D_FlipFlop d(Q[ii-1],clk,rst,Q[ii]);
            end
        end
    endgenerate 
endmodule
module TB;
    parameter N=32;
    reg rst;
    reg clk;
    wire [N-1:0]Q;
    always begin
        #5 clk=~clk;
    end
    Johnson_counter #(.N(N)) sample (rst,clk,Q);
    initial begin
        clk=0;
        rst<=0;
        #2 rst<=1;
        #500 $finish;
    end
    initial begin
        $monitor("%b", Q);
    end
    initial begin
        $dumpfile("Johnson_counter.vcd");
        $dumpvars(0,TB);
    end
endmodule

Question6/Johnson_counter.vcd
$date
	Mon May 20 19:39:33 2024
$end
$version
	Icarus Verilog
$end
$timescale
	1s
$end
$scope module TB $end
$var wire 32 ! Q [31:0] $end
$var reg 1 " clk $end
$var reg 1 # rst $end
$scope module sample $end
$var wire 1 " clk $end
$var wire 1 # rst $end
$var wire 32 $ Q [31:0] $end
$scope begin genblk1[0] $end
$scope begin genblk2 $end
$scope module d $end
$var wire 1 % D $end
$var wire 1 " clk $end
$var wire 1 # rst $end
$var reg 1 & Q $end
$upscope $end
$upscope $end
$upscope $end
$scope begin genblk1[1] $end
$scope begin genblk3 $end
$scope module d $end
$var wire 1 ' D $end
$var wire 1 " clk $end
$var wire 1 # rst $end
$var reg 1 ( Q $end
$upscope $end
$upscope $end
$upscope $end
$scope begin genblk1[2] $end
$scope begin genblk3 $end
$scope module d $end
$var wire 1 ) D $end
$var wire 1 " clk $end
$var wire 1 # rst $end
$var reg 1 * Q $end
$upscope $end
$upscope $end
$upscope $end
$scope begin genblk1[3] $end
$scope begin genblk3 $end
$scope module d $end
$var wire 1 + D $end
$var wire 1 " clk $end
$var wire 1 # rst $end
$var reg 1 , Q $end
$upscope $end
$upscope $end
$upscope $end
$scope begin genblk1[4] $end
$scope begin genblk3 $end
$scope module d $end
$var wire 1 - D $end
$var wire 1 " clk $end
$var wire 1 # rst $end
$var reg 1 . Q $end
$upscope $end
$upscope $end
$upscope $end
$scope begin genblk1[5] $end
$scope begin genblk3 $end
$scope module d $end
$var wire 1 / D $end
$var wire 1 " clk $end
$var wire 1 # rst $end
$var reg 1 0 Q $end
$upscope $end
$upscope $end
$upscope $end
$scope begin genblk1[6] $end
$scope begin genblk3 $end
$scope module d $end
$var wire 1 1 D $end
$var wire 1 " clk $end
$var wire 1 # rst $end
$var reg 1 2 Q $end
$upscope $end
$upscope $end
$upscope $end
$scope begin genblk1[7] $end
$scope begin genblk3 $end
$scope module d $end
$var wire 1 3 D $end
$var wire 1 " clk $end
$var wire 1 # rst $end
$var reg 1 4 Q $end
$upscope $end
$upscope $end
$upscope $end
$scope begin genblk1[8] $end
$scope begin genblk3 $end
$scope module d $end
$var wire 1 5 D $end
$var wire 1 " clk $end
$var wire 1 # rst $end
$var reg 1 6 Q $end
$upscope $end
$upscope $end
$upscope $end
$scope begin genblk1[9] $end
$scope begin genblk3 $end
$scope module d $end
$var wire 1 7 D $end
$var wire 1 " clk $end
$var wire 1 # rst $end
$var reg 1 8 Q $end
$upscope $end
$upscope $end
$upscope $end
$scope begin genblk1[10] $end
$scope begin genblk3 $end
$scope module d $end
$var wire 1 9 D $end
$var wire 1 " clk $end
$var wire 1 # rst $end
$var reg 1 : Q $end
$upscope $end
$upscope $end
$upscope $end
$scope begin genblk1[11] $end
$scope begin genblk3 $end
$scope module d $end
$var wire 1 ; D $end
$var wire 1 " clk $end
$var wire 1 # rst $end
$var reg 1 < Q $end
$upscope $end
$upscope $end
$upscope $end
$scope begin genblk1[12] $end
$scope begin genblk3 $end
$scope module d $end
$var wire 1 = D $end
$var wire 1 " clk $end
$var wire 1 # rst $end
$var reg 1 > Q $end
$upscope $end
$upscope $end
$upscope $end
$scope begin genblk1[13] $end
$scope begin genblk3 $end
$scope module d $end
$var wire 1 ? D $end
$var wire 1 " clk $end
$var wire 1 # rst $end
$var reg 1 @ Q $end
$upscope $end
$upscope $end
$upscope $end
$scope begin genblk1[14] $end
$scope begin genblk3 $end
$scope module d $end
$var wire 1 A D $end
$var wire 1 " clk $end
$var wire 1 # rst $end
$var reg 1 B Q $end
$upscope $end
$upscope $end
$upscope $end
$scope begin genblk1[15] $end
$scope begin genblk3 $end
$scope module d $end
$var wire 1 C D $end
$var wire 1 " clk $end
$var wire 1 # rst $end
$var reg 1 D Q $end
$upscope $end
$upscope $end
$upscope $end
$scope begin genblk1[16] $end
$scope begin genblk3 $end
$scope module d $end
$var wire 1 E D $end
$var wire 1 " clk $end
$var wire 1 # rst $end
$var reg 1 F Q $end
$upscope $end
$upscope $end
$upscope $end
$scope begin genblk1[17] $end
$scope begin genblk3 $end
$scope module d $end
$var wire 1 G D $end
$var wire 1 " clk $end
$var wire 1 # rst $end
$var reg 1 H Q $end
$upscope $end
$upscope $end
$upscope $end
$scope begin genblk1[18] $end
$scope begin genblk3 $end
$scope module d $end
$var wire 1 I D $end
$var wire 1 " clk $end
$var wire 1 # rst $end
$var reg 1 J Q $end
$upscope $end
$upscope $end
$upscope $end
$scope begin genblk1[19] $end
$scope begin genblk3 $end
$scope module d $end
$var wire 1 K D $end
$var wire 1 " clk $end
$var wire 1 # rst $end
$var reg 1 L Q $end
$upscope $end
$upscope $end
$upscope $end
$scope begin genblk1[20] $end
$scope begin genblk3 $end
$scope module d $end
$var wire 1 M D $end
$var wire 1 " clk $end
$var wire 1 # rst $end
$var reg 1 N Q $end
$upscope $end
$upscope $end
$upscope $end
$scope begin genblk1[21] $end
$scope begin genblk3 $end
$scope module d $end
$var wire 1 O D $end
$var wire 1 " clk $end
$var wire 1 # rst $end
$var reg 1 P Q $end
$upscope $end
$upscope $end
$upscope $end
$scope begin genblk1[22] $end
$scope begin genblk3 $end
$scope module d $end
$var wire 1 Q D $end
$var wire 1 " clk $end
$var wire 1 # rst $end
$var reg 1 R Q $end
$upscope $end
$upscope $end
$upscope $end
$scope begin genblk1[23] $end
$scope begin genblk3 $end
$scope module d $end
$var wire 1 S D $end
$var wire 1 " clk $end
$var wire 1 # rst $end
$var reg 1 T Q $end
$upscope $end
$upscope $end
$upscope $end
$scope begin genblk1[24] $end
$scope begin genblk3 $end
$scope module d $end
$var wire 1 U D $end
$var wire 1 " clk $end
$var wire 1 # rst $end
$var reg 1 V Q $end
$upscope $end
$upscope $end
$upscope $end
$scope begin genblk1[25] $end
$scope begin genblk3 $end
$scope module d $end
$var wire 1 W D $end
$var wire 1 " clk $end
$var wire 1 # rst $end
$var reg 1 X Q $end
$upscope $end
$upscope $end
$upscope $end
$scope begin genblk1[26] $end
$scope begin genblk3 $end
$scope module d $end
$var wire 1 Y D $end
$var wire 1 " clk $end
$var wire 1 # rst $end
$var reg 1 Z Q $end
$upscope $end
$upscope $end
$upscope $end
$scope begin genblk1[27] $end
$scope begin genblk3 $end
$scope module d $end
$var wire 1 [ D $end
$var wire 1 " clk $end
$var wire 1 # rst $end
$var reg 1 \ Q $end
$upscope $end
$upscope $end
$upscope $end
$scope begin genblk1[28] $end
$scope begin genblk3 $end
$scope module d $end
$var wire 1 ] D $end
$var wire 1 " clk $end
$var wire 1 # rst $end
$var reg 1 ^ Q $end
$upscope $end
$upscope $end
$upscope $end
$scope begin genblk1[29] $end
$scope begin genblk3 $end
$scope module d $end
$var wire 1 _ D $end
$var wire 1 " clk $end
$var wire 1 # rst $end
$var reg 1 ` Q $end
$upscope $end
$upscope $end
$upscope $end
$scope begin genblk1[30] $end
$scope begin genblk3 $end
$scope module d $end
$var wire 1 a D $end
$var wire 1 " clk $end
$var wire 1 # rst $end
$var reg 1 b Q $end
$upscope $end
$upscope $end
$upscope $end
$scope begin genblk1[31] $end
$scope begin genblk3 $end
$scope module d $end
$var wire 1 c D $end
$var wire 1 " clk $end
$var wire 1 # rst $end
$var reg 1 d Q $end
$upscope $end
$upscope $end
$upscope $end
$upscope $end
$upscope $end
$enddefinitions $end
#0
$dumpvars
0d
0c
0b
0a
0`
0_
0^
0]
0\
0[
0Z
0Y
0X
0W
0V
0U
0T
0S
0R
0Q
0P
0O
0N
0M
0L
0K
0J
0I
0H
0G
0F
0E
0D
0C
0B
0A
0@
0?
0>
0=
0<
0;
0:
09
08
07
06
05
04
03
02
01
00
0/
0.
0-
0,
0+
0*
0)
0(
0'
0&
1%
b0 $
0#
0"
b0 !
$end
#2
1#
#5
1'
b1 !
b1 $
1&
1"
#10
0"
#15
1)
b11 !
b11 $
1(
1"
#20
0"
#25
1+
b111 !
b111 $
1*
1"
#30
0"
#35
1-
b1111 !
b1111 $
1,
1"
#40
0"
#45
1/
b11111 !
b11111 $
1.
1"
#50
0"
#55
11
b111111 !
b111111 $
10
1"
#60
0"
#65
13
b1111111 !
b1111111 $
12
1"
#70
0"
#75
15
b11111111 !
b11111111 $
14
1"
#80
0"
#85
17
b111111111 !
b111111111 $
16
1"
#90
0"
#95
19
b1111111111 !
b1111111111 $
18
1"
#100
0"
#105
1;
b11111111111 !
b11111111111 $
1:
1"
#110
0"
#115
1=
b111111111111 !
b111111111111 $
1<
1"
#120
0"
#125
1?
b1111111111111 !
b1111111111111 $
1>
1"
#130
0"
#135
1A
b11111111111111 !
b11111111111111 $
1@
1"
#140
0"
#145
1C
b111111111111111 !
b111111111111111 $
1B
1"
#150
0"
#155
1E
b1111111111111111 !
b1111111111111111 $
1D
1"
#160
0"
#165
1G
b11111111111111111 !
b11111111111111111 $
1F
1"
#170
0"
#175
1I
b111111111111111111 !
b111111111111111111 $
1H
1"
#180
0"
#185
1K
b1111111111111111111 !
b1111111111111111111 $
1J
1"
#190
0"
#195
1M
b11111111111111111111 !
b11111111111111111111 $
1L
1"
#200
0"
#205
1O
b111111111111111111111 !
b111111111111111111111 $
1N
1"
#210
0"
#215
1Q
b1111111111111111111111 !
b1111111111111111111111 $
1P
1"
#220
0"
#225
1S
b11111111111111111111111 !
b11111111111111111111111 $
1R
1"
#230
0"
#235
1U
b111111111111111111111111 !
b111111111111111111111111 $
1T
1"
#240
0"
#245
1W
b1111111111111111111111111 !
b1111111111111111111111111 $
1V
1"
#250
0"
#255
1Y
b11111111111111111111111111 !
b11111111111111111111111111 $
1X
1"
#260
0"
#265
1[
b111111111111111111111111111 !
b111111111111111111111111111 $
1Z
1"
#270
0"
#275
1]
b1111111111111111111111111111 !
b1111111111111111111111111111 $
1\
1"
#280
0"
#285
1_
b11111111111111111111111111111 !
b11111111111111111111111111111 $
1^
1"
#290
0"
#295
1a
b111111111111111111111111111111 !
b111111111111111111111111111111 $
1`
1"
#300
0"
#305
1c
b1111111111111111111111111111111 !
b1111111111111111111111111111111 $
1b
1"
#310
0"
#315
0%
b11111111111111111111111111111111 !
b11111111111111111111111111111111 $
1d
1"
#320
0"
#325
0'
b11111111111111111111111111111110 !
b11111111111111111111111111111110 $
0&
1"
#330
0"
#335
0)
b11111111111111111111111111111100 !
b11111111111111111111111111111100 $
0(
1"
#340
0"
#345
0+
b11111111111111111111111111111000 !
b11111111111111111111111111111000 $
0*
1"
#350
0"
#355
0-
b11111111111111111111111111110000 !
b11111111111111111111111111110000 $
0,
1"
#360
0"
#365
0/
b11111111111111111111111111100000 !
b11111111111111111111111111100000 $
0.
1"
#370
0"
#375
01
b11111111111111111111111111000000 !
b11111111111111111111111111000000 $
00
1"
#380
0"
#385
03
b11111111111111111111111110000000 !
b11111111111111111111111110000000 $
02
1"
#390
0"
#395
05
b11111111111111111111111100000000 !
b11111111111111111111111100000000 $
04
1"
#400
0"
#405
07
b11111111111111111111111000000000 !
b11111111111111111111111000000000 $
06
1"
#410
0"
#415
09
b11111111111111111111110000000000 !
b11111111111111111111110000000000 $
08
1"
#420
0"
#425
0;
b11111111111111111111100000000000 !
b11111111111111111111100000000000 $
0:
1"
#430
0"
#435
0=
b11111111111111111111000000000000 !
b11111111111111111111000000000000 $
0<
1"
#440
0"
#445
0?
b11111111111111111110000000000000 !
b11111111111111111110000000000000 $
0>
1"
#450
0"
#455
0A
b11111111111111111100000000000000 !
b11111111111111111100000000000000 $
0@
1"
#460
0"
#465
0C
b11111111111111111000000000000000 !
b11111111111111111000000000000000 $
0B
1"
#470
0"
#475
0E
b11111111111111110000000000000000 !
b11111111111111110000000000000000 $
0D
1"
#480
0"
#485
0G
b11111111111111100000000000000000 !
b11111111111111100000000000000000 $
0F
1"
#490
0"
#495
0I
b11111111111111000000000000000000 !
b11111111111111000000000000000000 $
0H
1"
